ati_sdk/__init__.py
ati_sdk/config.py
ati_sdk/otel.py
ati_sdk/semantics.py
ati_sdk-0.1.1.dist-info/METADATA
ati_sdk-0.1.1.dist-info/WHEEL
ati_sdk-0.1.1.dist-info/RECORD
