Metadata-Version: 2.4
Name: ati-sdk
Version: 0.1.1
Summary: ATI SDK: shared config + semantic conventions helpers for agent-aware OpenTelemetry tracing
Project-URL: Homepage, https://iocane.ai
Project-URL: Repository, https://github.com/iocane-ai/ati-integrations
Requires-Python: >=3.10
Requires-Dist: opentelemetry-api>=1.24.0
Requires-Dist: opentelemetry-sdk>=1.24.0
